vsaa/README.md
vsaa/__init__.py
vsaa/deinterlacers.py
vsaa/funcs.py
vsaa/py.typed
vsdeband/CHANGELOG.md
vsdeband/README.md
vsdeband/__init__.py
vsdeband/debanders.py
vsdeband/mask.py
vsdeband/noise.py
vsdeband/py.typed
vsdehalo/README.md
vsdehalo/__init__.py
vsdehalo/alpha.py
vsdehalo/border.py
vsdehalo/denoise.py
vsdehalo/mask.py
vsdehalo/py.typed
vsdehalo/warp.py
vsdeinterlace/README.md
vsdeinterlace/__init__.py
vsdeinterlace/blending.py
vsdeinterlace/enums.py
vsdeinterlace/funcs.py
vsdeinterlace/ivtc.py
vsdeinterlace/py.typed
vsdeinterlace/qtgmc.py
vsdeinterlace/utils.py
vsdenoise/README.md
vsdenoise/__init__.py
vsdenoise/blockmatch.py
vsdenoise/deblock.py
vsdenoise/fft.py
vsdenoise/freqs.py
vsdenoise/funcs.py
vsdenoise/nlm.py
vsdenoise/postprocess.py
vsdenoise/prefilters.py
vsdenoise/py.typed
vsdenoise/regress.py
vsdenoise/mvtools/__init__.py
vsdenoise/mvtools/enums.py
vsdenoise/mvtools/motion.py
vsdenoise/mvtools/mvtools.py
vsdenoise/mvtools/presets.py
vsdenoise/mvtools/utils.py
vsexprtools/README.md
vsexprtools/__init__.py
vsexprtools/error.py
vsexprtools/exprop.py
vsexprtools/funcs.py
vsexprtools/py.typed
vsexprtools/util.py
vsexprtools/inline/__init__.py
vsexprtools/inline/error.py
vsexprtools/inline/helpers.py
vsexprtools/inline/manager.py
vsexprtools/inline/polyfills.py
vskernels/README.md
vskernels/__init__.py
vskernels/docs.py
vskernels/exceptions.py
vskernels/py.typed
vskernels/types.py
vskernels/util.py
vskernels/abstract/__init__.py
vskernels/abstract/base.py
vskernels/abstract/complex.py
vskernels/abstract/custom.py
vskernels/kernels/__init__.py
vskernels/kernels/placebo.py
vskernels/kernels/custom/__init__.py
vskernels/kernels/custom/bicubic.py
vskernels/kernels/custom/helpers.py
vskernels/kernels/custom/spline.py
vskernels/kernels/custom/various.py
vskernels/kernels/zimg/__init__.py
vskernels/kernels/zimg/abstract.py
vskernels/kernels/zimg/bicubic.py
vskernels/kernels/zimg/spline.py
vskernels/kernels/zimg/various.py
vsmasktools/README.md
vsjetpack-0.8.3.dist-info/METADATA
vsjetpack-0.8.3.dist-info/WHEEL
vsjetpack-0.8.3.dist-info/licenses/LICENSE
vsjetpack-0.8.3.dist-info/RECORD
