Metadata-Version: 2.4
Name: vsjetpack
Version: 0.8.3
Summary: Full suite of filters, wrappers, and helper functions for filtering video using VapourSynth
Project-URL: Source Code, https://github.com/Jaded-Encoding-Thaumaturgy/vs-jetpack
Project-URL: Contact, https://discord.gg/XTpc6Fa9eB
Author: Jaded Encoding Thaumaturgy
Maintainer-email: Jaded Encoding Thaumaturgy <jaded.encoding.thaumaturgy@gmail.com>
License-Expression: MIT
License-File: LICENSE
Classifier: Development Status :: 5 - Production/Stable
Classifier: License :: OSI Approved :: MIT License
Classifier: Natural Language :: English
Classifier: Operating System :: OS Independent
Classifier: Programming Language :: Python :: 3
Classifier: Programming Language :: Python :: 3 :: Only
Classifier: Topic :: Multimedia :: Graphics
Classifier: Typing :: Typed
Requires-Python: >=3.10
Requires-Dist: jetpytools~=1.7.3
Requires-Dist: numpy>=2.0.0
Requires-Dist: rich>=12.6.0
Requires-Dist: scipy>=1.10.0
Requires-Dist: typing-extensions>=4.12.2
Requires-Dist: vapoursynth>=67
